README.md
setup.cfg
setup.py
phstglib/__init__.py
phstglib.egg-info/PKG-INFO
phstglib.egg-info/SOURCES.txt
phstglib.egg-info/dependency_links.txt
phstglib.egg-info/top_level.txt
phstglib/map/__init__.py
phstglib/map/baidu.py
phstglib/map/gaode.py
phstglib/map/route_plan.py
phstglib/map/util.py
phstglib/math/__init__.py
phstglib/math/calculate.py
phstglib/math/shape.py