Metadata-Version: 1.0
Name: phstglib
Version: 0.0.5
Summary: a library for puhui strategy
Home-page: https://git.xiaojukeji.com/intell_strategy/dj_stg
Author: Kuida Wu
Author-email: wukuida@didichuxing.com
License: MIT License
Keywords: puhui dj strategy
Platform: any
